tabforge/__init__.py
tabforge/error.py
tabforge/filters.py
tabforge/main.py
tabforge/render.py
tabforge-0.0.4.dist-info/LICENSE
tabforge-0.0.4.dist-info/METADATA
tabforge-0.0.4.dist-info/WHEEL
tabforge-0.0.4.dist-info/entry_points.txt
tabforge-0.0.4.dist-info/RECORD
